evaluatr/__init__.py
evaluatr/_modidx.py
evaluatr/downloaders.py
evaluatr/enrichr.py
evaluatr/frameworks.py
evaluatr/mappr.py
evaluatr/ocr.py
evaluatr/readers.py
evaluatr-0.7.2.dist-info/licenses/LICENSE
evaluatr-0.7.2.dist-info/METADATA
evaluatr-0.7.2.dist-info/WHEEL
evaluatr-0.7.2.dist-info/entry_points.txt
evaluatr-0.7.2.dist-info/top_level.txt
evaluatr-0.7.2.dist-info/RECORD
