Metadata-Version: 2.4
Name: evaluatr
Version: 0.7.2
Summary: Streamline policy evaluation workflows with AI-driven analysis and evaluation framework-agnostic processing
Home-page: https://github.com/franckalbinet/evaluatr
Author: Franck Albinet
Author-email: franckalbinet@gmail.com
License: Apache Software License 2.0
Keywords: nbdev jupyter notebook python
Classifier: Development Status :: 4 - Beta
Classifier: Intended Audience :: Developers
Classifier: Natural Language :: English
Classifier: Programming Language :: Python :: 3.9
Classifier: Programming Language :: Python :: 3.10
Classifier: Programming Language :: Python :: 3.11
Classifier: Programming Language :: Python :: 3.12
Classifier: License :: OSI Approved :: Apache Software License
Requires-Python: >=3.9
License-File: LICENSE
Requires-Dist: fastcore
Requires-Dist: pandas
Requires-Dist: openpyxl
Requires-Dist: rich
Requires-Dist: requests
Requires-Dist: fastprogress
Requires-Dist: mistralai
Requires-Dist: dotenv
Requires-Dist: tqdm
Requires-Dist: dspy
Requires-Dist: toolslm
Requires-Dist: fastlite
Requires-Dist: lisette
Requires-Dist: apsw==3.49.1.0
Provides-Extra: dev
Requires-Dist: nbdev; extra == "dev"
Requires-Dist: ipykernel; extra == "dev"
Requires-Dist: matplotlib; extra == "dev"
Requires-Dist: seaborn; extra == "dev"
Dynamic: author
Dynamic: author-email
Dynamic: classifier
Dynamic: description
Dynamic: description-content-type
Dynamic: home-page
Dynamic: keywords
Dynamic: license
Dynamic: license-file
Dynamic: provides-extra
Dynamic: requires-dist
Dynamic: requires-python
Dynamic: summary
